tygle/__init__.py
tygle/base/__init__.py
tygle/base/api.py
tygle/base/chain.py
tygle/base/requests/__init__.py
tygle/base/requests/data_request.py
tygle/base/requests/download_request.py
tygle/base/requests/request.py
tygle/base/requests/upload_request.py
tygle/base/resource.py
tygle/base/response.py
tygle/base/rest.py
tygle/base/rests.py
tygle/client.py
tygle-0.2.0.dist-info/WHEEL
tygle-0.2.0.dist-info/METADATA
tygle-0.2.0.dist-info/RECORD
