Metadata-Version: 2.1
Name: tygle
Version: 0.2.0
Summary: Typed Google or simply tygle.
Home-page: https://github.com/typed-google/tygle
Author: shmookoff
Author-email: shmookoff@gmail.com
Requires-Python: >=3.10,<4.0
Classifier: Programming Language :: Python :: 3
Classifier: Programming Language :: Python :: 3.10
Provides-Extra: docs
Provides-Extra: drive
Provides-Extra: sheets
Requires-Dist: aiogoogle (>=4.2.0,<5.0.0)
Requires-Dist: pydantic (>=1.9.0,<2.0.0)
Requires-Dist: tygle-docs (>=0.1.0,<0.2.0); extra == "docs"
Requires-Dist: tygle-drive (>=0.1.0,<0.2.0); extra == "drive"
Requires-Dist: tygle-sheets (>=0.1.0,<0.2.0); extra == "sheets"
Project-URL: Repository, https://github.com/typed-google/tygle
